salamanca/__init__.py
salamanca/cli.py
salamanca/currency.py
salamanca/data.py
salamanca/ineq.py
salamanca/utils.py
salamanca-0.2.0.dist-info/LICENSE
salamanca-0.2.0.dist-info/METADATA
salamanca-0.2.0.dist-info/WHEEL
salamanca-0.2.0.dist-info/entry_points.txt
salamanca-0.2.0.dist-info/top_level.txt
salamanca-0.2.0.dist-info/RECORD
