Metadata-Version: 2.1
Name: salamanca
Version: 0.2.0
Summary: Provides access to and operations on commonly used socio-economic indicators
Home-page: http://github.com/gidden/salamanca
Author: salamanca authors
Author-email: matthew.gidden@gmail.com
License: Apache 2.0
Platform: UNKNOWN
Requires-Dist: pandas
Requires-Dist: pyomo
Requires-Dist: numpy
Requires-Dist: scipy
Requires-Dist: requests
Provides-Extra: doc
Requires-Dist: sphinx ; extra == 'doc'
Requires-Dist: cloud-sptheme ; extra == 'doc'
Requires-Dist: nbsphinx ; extra == 'doc'
Requires-Dist: numpydoc ; extra == 'doc'
Requires-Dist: sphinxcontrib-bibtex (<2.0) ; extra == 'doc'
Requires-Dist: sphinxcontrib-programoutput ; extra == 'doc'
Provides-Extra: test
Requires-Dist: pytest ; extra == 'test'
Requires-Dist: pytest-cov ; extra == 'test'
